tarproc-0.0.6.data/scripts/tar2tsv
tarproc-0.0.6.data/scripts/tarcats
tarproc-0.0.6.data/scripts/tarfirst
tarproc-0.0.6.data/scripts/tarmix
tarproc-0.0.6.data/scripts/tarpcat
tarproc-0.0.6.data/scripts/tarproc
tarproc-0.0.6.data/scripts/tarshow
tarproc-0.0.6.data/scripts/tarsort
tarproc-0.0.6.data/scripts/tarsplit
tarproc-0.0.6.data/scripts/tsv2tar
tarproclib/gopen.py
tarproclib/paths.py
tarproclib/proc.py
tarproclib/reader.py
tarproclib/writer.py
tarproclib/zcom.py
tarproc-0.0.6.dist-info/LICENSE
tarproc-0.0.6.dist-info/METADATA
tarproc-0.0.6.dist-info/WHEEL
tarproc-0.0.6.dist-info/top_level.txt
tarproc-0.0.6.dist-info/RECORD
