Metadata-Version: 2.1
Name: tarproc
Version: 0.0.6
Summary: Big data data processing for tar archives.
Home-page: http://github.com/tmbdev/webdataset
Author: Thomas Breuel
Author-email: tmbdev+removeme@gmail.com
License: MIT
Keywords: POSIX tar,map reduce,object store,deep learning
Platform: UNKNOWN
Classifier: Development Status :: 3 - Alpha
Classifier: License :: OSI Approved :: BSD License
Classifier: Programming Language :: Python :: 3.6
Classifier: Programming Language :: Python :: 3.7
Requires-Python: >=3.6
Requires-Dist: future
Requires-Dist: msgpack
Requires-Dist: braceexpand
Requires-Dist: simplejson
Requires-Dist: pyzmq
Requires-Dist: numpy
Requires-Dist: pyyaml
